{
  "name": "",
  "type": "avantage",
  "img": "systems/knight/assets/icons/avantage.svg",
  "system": {
    "description": "",
    "type": "standard",
    "bonus": {
      "sante": 0,
      "espoir": 0,
      "initiative": {
        "dice": 0,
        "fixe": 0,
        "ifEmbuscade": {
          "has": false,
          "dice": 0,
          "fixe": 0
        }
      },
      "recuperation": {
        "sante": 0,
        "armure": 0,
        "energie": 0,
        "espoir": 0
      },
      "coutsReduits": {
        "has": false,
        "aspect": {
          "divise": 0,
          "value": 0
        },
        "caracteristique": {
          "divise": 0,
          "value": 0
        }
      }
    }
  },
  "effects": [ ]
}
